rasterutils/__init__.py
rasterutils/cli.py
rasterutils/reprojection.py
rasterutils-0.2.0.dist-info/licenses/LICENSE
rasterutils-0.2.0.dist-info/METADATA
rasterutils-0.2.0.dist-info/WHEEL
rasterutils-0.2.0.dist-info/top_level.txt
rasterutils-0.2.0.dist-info/RECORD
