Metadata-Version: 2.4
Name: rasterutils
Version: 0.2.0
Summary: A utility library for raster image reprojection
Author-email: Your Name <you@example.com>
License: MIT
Requires-Python: >=3.9
License-File: LICENSE
Requires-Dist: rasterio>=1.3.0
Provides-Extra: cli
Requires-Dist: click>=8.0; extra == "cli"
Provides-Extra: dev
Requires-Dist: pytest; extra == "dev"
Requires-Dist: black; extra == "dev"
Requires-Dist: ruff; extra == "dev"
Requires-Dist: mypy; extra == "dev"
Requires-Dist: coverage; extra == "dev"
Dynamic: license-file
